remnapi/__init__.py
remnapi/api_client.py
remnapi/api_requests.py
remnapi/controllers/__init__.py
remnapi/controllers/nodes.py
remnapi/controllers/subscriptions.py
remnapi/controllers/token.py
remnapi/controllers/users.py
remnapi-0.1.19.dist-info/LICENSE
remnapi-0.1.19.dist-info/METADATA
remnapi-0.1.19.dist-info/WHEEL
remnapi-0.1.19.dist-info/top_level.txt
remnapi-0.1.19.dist-info/RECORD
