Metadata-Version: 2.2
Name: remnapi
Version: 0.1.19
Summary: API Remnawave for Python
Home-page: https://github.com/nvwrist/remnapi
Author: nvwrist
Author-email: faxonq@gmail.com
Classifier: Programming Language :: Python :: 3
Classifier: License :: OSI Approved :: MIT License
Classifier: Operating System :: OS Independent
Requires-Python: >=3.7
License-File: LICENSE
Requires-Dist: certifi
Requires-Dist: charset-normalizer
Requires-Dist: idna
Requires-Dist: python-dotenv
Requires-Dist: requests
Requires-Dist: shortuuid
Requires-Dist: urllib3
Requires-Dist: aiohttp
Dynamic: author
Dynamic: author-email
Dynamic: classifier
Dynamic: description
Dynamic: description-content-type
Dynamic: home-page
Dynamic: requires-dist
Dynamic: requires-python
Dynamic: summary
